alvin_cli/__init__.py
alvin_cli/cli.py
alvin_cli/cli__test.py
alvin_cli/dbt.py
alvin_cli/config/__init__.py
alvin_cli/config/loader.py
alvin_cli/config/settings.py
alvin_cli/datafakehouse/__init__.py
alvin_cli/datafakehouse/methods.py
alvin_cli/datafakehouse/models.py
alvin_cli/datafakehouse/grpc_client/__init__.py
alvin_cli/datafakehouse/grpc_client/datafakehouse_client.py
alvin_cli/datafakehouse/grpc_generated/__init__.py
alvin_cli/datafakehouse/grpc_generated/datafakehouse_pb2.py
alvin_cli/datafakehouse/grpc_generated/datafakehouse_pb2.pyi
alvin_cli/datafakehouse/grpc_generated/datafakehouse_pb2_grpc.py
alvin_cli/utils/__init__.py
alvin_cli/utils/common_arguments.py
alvin_cli/utils/helper_functions.py
alvin_simple_cli-0.0.37.dist-info/LICENSE
alvin_simple_cli-0.0.37.dist-info/METADATA
alvin_simple_cli-0.0.37.dist-info/WHEEL
alvin_simple_cli-0.0.37.dist-info/entry_points.txt
alvin_simple_cli-0.0.37.dist-info/top_level.txt
alvin_simple_cli-0.0.37.dist-info/RECORD
