Metadata-Version: 2.2
Name: alvin_simple_cli
Version: 0.0.37
Summary: Alvin Simple CLI
License:                     GNU AFFERO GENERAL PUBLIC LICENSE
Classifier: Programming Language :: Python :: 3.8
Classifier: Programming Language :: Python :: 3.9
Classifier: Programming Language :: Python :: 3.10
Classifier: Programming Language :: Python :: 3.11
Classifier: Programming Language :: Python :: Implementation :: PyPy
Requires-Python: >=3.8
License-File: LICENSE
Requires-Dist: rich==13.6.0
Requires-Dist: gitpython==3.1.41
Requires-Dist: requests>=2.28.0
Requires-Dist: typer==0.9.0
Requires-Dist: python-dotenv==1.0.0
Requires-Dist: grpcio==1.63.0
Requires-Dist: grpcio-tools==1.63.0
Requires-Dist: google-auth==2.23.3
